.hgignore
.hgtags
HISTORY.rst
README.rst
mercurial_dynamic_username.py
noxfile.py
setup.py
mercurial_dynamic_username.egg-info/PKG-INFO
mercurial_dynamic_username.egg-info/SOURCES.txt
mercurial_dynamic_username.egg-info/dependency_links.txt
mercurial_dynamic_username.egg-info/requires.txt
mercurial_dynamic_username.egg-info/top_level.txt
mercurial_dynamic_username.egg-info/zip-safe
tests/basic.t
tests/conflicting.t