Metadata-Version: 2.1
Name: mercurial_dynamic_username
Version: 1.1.2
Summary: Mercurial Dynamic Username Extension
Home-page: https://foss.heptapod.net/mercurial/mercurial-dynamic_username
Author: Marcin Kasperski
Author-email: Marcin.Kasperski@mekk.waw.pl
License: BSD
Keywords: mercurial hg username extension
Classifier: Development Status :: 4 - Beta
Classifier: Environment :: Console
Classifier: Intended Audience :: Developers
Classifier: License :: DFSG approved
Classifier: License :: OSI Approved :: BSD License
Classifier: Programming Language :: Python :: 2
Classifier: Programming Language :: Python :: 3
Classifier: Operating System :: OS Independent
Classifier: Topic :: Software Development :: Version Control
Requires-Dist: mercurial_extension_utils>=1.5.0
